{
    "suggest.snippetIndicator": "",
    "diagnostic.errorSign": "❌",
    "diagnostic.warningSign": "⚠️",
    "diagnostic.infoSign": "ℹ️",
    "diagnostic.hintSign": "💡",
    "java.trace.server": "verbose",
    "java.format.settings.url": "https://raw.githubusercontent.com/google/styleguide/gh-pages/eclipse-java-google-style.xml",
    "coc.preferences.formatOnSaveFiletypes": [
        "kotlin",
        "java",
        "json",
        "jsonc",
        "rust",
        "yaml",
        "typescript"
    ],
    "languageserver": {
        "kotlin": {
            "command": "kotlin-language-server",
            "filetypes": [
                "kotlin"
            ]
        },
        "haskell": {
            "command": "hie-wrapper",
            "args": [
                "--lsp"
            ],
            "rootPatterns": [
                "stack.yaml",
                "cabal.config",
                "package.yaml"
            ],
            "filetypes": [
                "hs",
                "lhs",
                "haskell"
            ],
            "initializationOptions": {
                "languageServerHaskell": {
                    "hlintOn": true
                }
            }
        },
        "golang": {
            "command": "gopls",
            "filetypes": [
                "go"
            ],
            "rootPatterns": [
                "go.mod"
            ]
        },
        "ccls": {
            "command": "ccls",
            "filetypes": [
                "c",
                "cpp",
                "objc",
                "objcpp"
            ],
            "rootPatterns": [
                ".ccls",
                "compile_commands.json",
                ".vim/",
                ".git/",
                ".hg/"
            ],
            "initializationOptions": {
                "cache": {
                    "directory": "/tmp/ccls"
                }
            }
        }
    }
}
